beancount_exporter/__init__.py
beancount_exporter/formats/__init__.py
beancount_exporter/formats/json_processor.py
beancount_exporter/formats/pgcopy_processor/__init__.py
beancount_exporter/formats/pgcopy_processor/configs.py
beancount_exporter/formats/pgcopy_processor/data_types.py
beancount_exporter/formats/pgcopy_processor/processor.py
beancount_exporter/formats/pgcopy_processor/tables.py
beancount_exporter/formats/pgcopy_processor/utils.py
beancount_exporter/formats/processor.py
beancount_exporter/main.py
beancount_exporter/utils.py
beancount_exporter-3.0.0.dist-info/LICENSE
beancount_exporter-3.0.0.dist-info/METADATA
beancount_exporter-3.0.0.dist-info/WHEEL
beancount_exporter-3.0.0.dist-info/RECORD
